simple_add_becky/__init__.py
simple_add_becky/add.py
simple_add_becky-0.1.0.dist-info/METADATA
simple_add_becky-0.1.0.dist-info/WHEEL
simple_add_becky-0.1.0.dist-info/top_level.txt
simple_add_becky-0.1.0.dist-info/RECORD
