Metadata-Version: 2.4
Name: simple_add_becky
Version: 0.1.0
Summary: A simple example package that adds two numbers.
Author: Rebecca Koleth
Author-email: Rebecca Koleth <rebeccakoleth@gmail.com>
License: MIT
Requires-Python: >=3.7
